Metadata-Version: 2.1
Name: udrparser
Version: 0.1.7
Summary: A simple package to get FQDN IP addresses
Home-page: UNKNOWN
Author: Arvind Ravish
Author-email: arvind.ravish@gmail.com
License: UNKNOWN
Platform: UNKNOWN
Classifier: Programming Language :: Python :: 3
Classifier: License :: OSI Approved :: MIT License
Classifier: Operating System :: OS Independent
